LICENSE
MANIFEST.in
README.rst
setup.py
chembl_compatibility/__init__.py
chembl_compatibility/models.py
chembl_compatibility/tests.py
chembl_compatibility.egg-info/PKG-INFO
chembl_compatibility.egg-info/SOURCES.txt
chembl_compatibility.egg-info/dependency_links.txt
chembl_compatibility.egg-info/not-zip-safe
chembl_compatibility.egg-info/requires.txt
chembl_compatibility.egg-info/top_level.txt