Metadata-Version: 1.1
Name: chembl-compatibility
Version: 0.5.5
Summary: Compatibility layer for running webservices from outside ChEMBL
Home-page: https://www.ebi.ac.uk/chembl/
Author: Michal Nowotka
Author-email: mnowotka@ebi.ac.uk
License: Apache Software License
Platform: Linux
Classifier: Development Status :: 2 - Pre-Alpha
Classifier: Environment :: Web Environment
Classifier: Framework :: Django
Classifier: Intended Audience :: Developers
Classifier: License :: OSI Approved :: Apache Software License
Classifier: Operating System :: POSIX :: Linux
Classifier: Programming Language :: Python :: 2.7
Classifier: Topic :: Scientific/Engineering :: Chemistry
